MANIFEST.in
README.txt
setup.py
docs/HISTORY.txt
src/infrae/__init__.py
src/infrae.comethods.egg-info/PKG-INFO
src/infrae.comethods.egg-info/SOURCES.txt
src/infrae.comethods.egg-info/dependency_links.txt
src/infrae.comethods.egg-info/namespace_packages.txt
src/infrae.comethods.egg-info/not-zip-safe
src/infrae.comethods.egg-info/requires.txt
src/infrae.comethods.egg-info/top_level.txt
src/infrae/comethods/__init__.py
src/infrae/comethods/decorators.py