Metadata-Version: 1.0
Name: infrae.comethods
Version: 1.0
Summary: Sugar around Python generators and context managers
Home-page: http://infrae.com/products/silva
Author: Infrae
Author-email: info@infrae.com
License: BSD
Keywords: comethod generator context manager
Platform: UNKNOWN
Classifier: Framework :: Zope2
Classifier: License :: OSI Approved :: BSD License
Classifier: Programming Language :: Python
Classifier: Topic :: Software Development :: Libraries :: Python Modules
